add_trailing_comma/__init__.py
add_trailing_comma/__main__.py
add_trailing_comma/_ast_helpers.py
add_trailing_comma/_data.py
add_trailing_comma/_main.py
add_trailing_comma/_token_helpers.py
add_trailing_comma/_plugins/__init__.py
add_trailing_comma/_plugins/_with.py
add_trailing_comma/_plugins/calls.py
add_trailing_comma/_plugins/classes.py
add_trailing_comma/_plugins/functions.py
add_trailing_comma/_plugins/imports.py
add_trailing_comma/_plugins/literals.py
add_trailing_comma/_plugins/match.py
add_trailing_comma/_plugins/pep695.py
add_trailing_comma-4.0.0.dist-info/LICENSE
add_trailing_comma-4.0.0.dist-info/METADATA
add_trailing_comma-4.0.0.dist-info/WHEEL
add_trailing_comma-4.0.0.dist-info/entry_points.txt
add_trailing_comma-4.0.0.dist-info/top_level.txt
add_trailing_comma-4.0.0.dist-info/RECORD
