Metadata-Version: 2.1
Name: add_trailing_comma
Version: 4.0.0
Summary: Automatically add trailing commas to calls and literals
Home-page: https://github.com/asottile/add-trailing-comma
Author: Anthony Sottile
Author-email: asottile@umich.edu
License: MIT
Classifier: Programming Language :: Python :: 3
Classifier: Programming Language :: Python :: 3 :: Only
Classifier: Programming Language :: Python :: Implementation :: CPython
Classifier: Programming Language :: Python :: Implementation :: PyPy
Requires-Python: >=3.10
License-File: LICENSE
Requires-Dist: tokenize-rt>=3.0.1
